pyopenstates/__init__.py
pyopenstates/config.py
pyopenstates/core.py
pyopenstates/downloads.py
pyopenstates-2.3.1.dist-info/LICENSE
pyopenstates-2.3.1.dist-info/WHEEL
pyopenstates-2.3.1.dist-info/METADATA
pyopenstates-2.3.1.dist-info/RECORD
