Metadata-Version: 2.1
Name: pyopenstates
Version: 2.3.1
Summary: A Python module for accessing the Open States API & bulk data.
Home-page: https://github.com/openstates/pyopenstates
License: Apache-2.0
Author: James Turk
Author-email: james@openstates.org
Requires-Python: >=3.7.1,<4.0.0
Classifier: Intended Audience :: Developers
Classifier: Intended Audience :: Legal Industry
Classifier: Intended Audience :: Science/Research
Classifier: License :: OSI Approved :: Apache Software License
Classifier: Operating System :: OS Independent
Classifier: Programming Language :: Python :: 3
Classifier: Programming Language :: Python :: 3.10
Classifier: Programming Language :: Python :: 3.7
Classifier: Programming Language :: Python :: 3.8
Classifier: Programming Language :: Python :: 3.9
Classifier: Topic :: Sociology :: History
Provides-Extra: pandas
Requires-Dist: pandas (>=1.3.4,<2.0.0); extra == "pandas"
Requires-Dist: python-dateutil (>=2.8.2,<3.0.0)
Requires-Dist: requests (>=2.26.0,<3.0.0)
Project-URL: Repository, https://github.com/openstates/pyopenstates
